<?xml version="1.0" encoding="GBK"?><root><head><code>1</code><message>数据查询成功</message><rownum>1</rownum></head><body><vehispara id="0"><xh>14040020036357</xh><hpzl>01</hpzl><hphm>晋DB2715</hphm><clpp1>解放牌</clpp1><clxh>CA4256P1K2T1E5A80</clxh><clpp2></clpp2><gcjk>A</gcjk><zzg>156</zzg><zzcmc>中国第一汽车集团有限公司</zzcmc><clsbdh>LFWSRURH8LAP03766</clsbdh><fdjh>7520F035550</fdjh><cllx>Q11</cllx><csys>E</csys><syxz>F</syxz><sfzmhm>911404********319X</sfzmhm><sfzmmc>N</sfzmmc><syr>潞城市承昌通商贸有限公司</syr><ccdjrq>2020/7/27 13:40:44</ccdjrq><djrq>2020/7/26 0:00:00</djrq><yxqz>2021/7/31 0:00:00</yxqz><qzbfqz>2035/7/27 0:00:00</qzbfqz><fzjg>晋D</fzjg><glbm>140400000400</glbm><bxzzrq>2021/7/26 0:00:00</bxzzrq><zt>G</zt><dybj></dybj><fdjxh>WP10H400E50</fdjxh><rlzl>B</rlzl><pl>9500</pl><gl>294</gl><zxxs>1</zxxs><cwkc>6675</cwkc><cwkk>2490</cwkk><cwkg>3290</cwkg><hxnbcd></hxnbcd><hxnbkd></hxnbkd><hxnbgd></hxnbgd><gbthps>3</gbthps><zs>3</zs><zj>4500</zj><qlj>2020</qlj><hlj>1847</hlj><ltgg>12R22.5 18PR</ltgg><lts>10</lts><zzl></zzl><zbzl>8415</zbzl><hdzzl></hdzzl><hdzk></hdzk><zqyzl>40000</zqyzl><qpzk>2</qpzk><hpzk></hpzk><hbdbqk>GB17691-2005国Ⅴ,GB3847-2005</hbdbqk><ccrq>2020/6/30 0:00:00</ccrq><clyt>P1</clyt><ytsx>9</ytsx><xszbh>1460013383773</xszbh><jyhgbzbh>211404327640</jyhgbzbh></vehispara></body></root>